ss_pybind11-0.8.40.dist-info/RECORD
ss_pybind11-0.8.40.dist-info/WHEEL
ss_pybind11-0.8.40.dist-info/METADATA
ss_pybind11-0.8.40.dist-info/licenses/LICENSE
ss_pybind11/_version.pyi
ss_pybind11/_core.pyi
ss_pybind11/_version.py
ss_pybind11/__init__.py
ss_pybind11/py.typed
ss_pybind11/_core.cpython-310-darwin.so
