Metadata-Version: 2.1
Name: ss_pybind11
Version: 0.8.40
Summary: A template of serious scaffold family based on pybind11.
Author-Email: "l.feng" <msclock@126.com>
License: MIT
Classifier: Intended Audience :: Science/Research
Classifier: Intended Audience :: Developers
Classifier: License :: OSI Approved :: MIT License
Classifier: Operating System :: OS Independent
Classifier: Programming Language :: Python
Classifier: Programming Language :: Python :: 3
Classifier: Programming Language :: Python :: 3 :: Only
Classifier: Programming Language :: Python :: 3.8
Classifier: Programming Language :: Python :: 3.9
Classifier: Programming Language :: Python :: 3.10
Classifier: Programming Language :: Python :: 3.11
Classifier: Programming Language :: Python :: 3.12
Classifier: Programming Language :: Python :: 3.13
Classifier: Topic :: Scientific/Engineering
Classifier: Typing :: Typed
Project-URL: Homepage, https://github.com/serious-scaffold/ss-pybind11
Project-URL: Bug Tracker, https://github.com/serious-scaffold/ss-pybind11/issues
Project-URL: Discussions, https://github.com/serious-scaffold/ss-pybind11/discussions
Project-URL: Changelog, https://github.com/serious-scaffold/ss-pybind11/releases
Requires-Python: >=3.8
Requires-Dist: typing-extensions>=3.10.0; python_version < "3.9"
Requires-Dist: importlib_metadata>=1.4
Provides-Extra: test
Requires-Dist: pytest>=6; extra == "test"
Requires-Dist: pytest-cov>=3; extra == "test"
Provides-Extra: dev
Requires-Dist: pytest>=6; extra == "dev"
Requires-Dist: pytest-cov>=3; extra == "dev"
Provides-Extra: docs
Requires-Dist: sphinx>=7.0; extra == "docs"
Requires-Dist: myst_parser>=0.13; extra == "docs"
Requires-Dist: sphinx_copybutton; extra == "docs"
Requires-Dist: sphinx_autodoc_typehints; extra == "docs"
Requires-Dist: furo>=2023.08.17; extra == "docs"
